Workbook
Name Slicer_Month: #N/A
Name Slicer_Product: #N/A
Name Slicer_Region: #N/A

Sheet Average Logistics
A1: Depot | B1: Count logistics
A2: Apapa | B2: 697375.05
A3: Ibadan | B3: 680424.64
A4: Port Harcourt | B4: 642323.16
A5: Calabar | B5: 649483.79
A6: Kano | B6: 675852.24
A7: Kaduna | B7: 743994.66

Sheet Forex Rate
A1: Month Name | B1: Clean FX
A2: March | B2: 1405.2778
A3: February | B3: 1390.59
A4: April | B4: 1422.0742
A5: May | B5: 1401.2142
A6: January | B6: 1400.2038
A7: June | B7: 1388.6643

Sheet Average Selling Price
A1: Product | B1: Month Name | C1: S.Price
A2: DPK | B2: March | C2: 657.78467
A3: DPK | B3: February | C3: 636.86222
A4: DPK | B4: April | C4: 635.94176
A5: DPK | B5: May | C5: 691.41765
A6: AGO | B6: May | C6: 673.38353
A7: AGO | B7: January | C7: 638.36071
A8: AGO | B8: June | C8: 630.69214
A9: DPK | B9: June | C9: 664.1225
A10: PMS | B10: May | C10: 597.57818
A11: PMS | B11: March | C11: 652.607
A12: PMS | B12: January | C12: 685.55333
A13: PMS | B13: June | C13: 651.21364
... A19: AGO | B19: February | C19: 706.51769

Sheet Average Cost price
A1: Product | B1: Month Name | C1: Cost Price Clean
A2: DPK | B2: March | C2: 600.8
A3: DPK | B3: February | C3: 549.66667
A4: DPK | B4: April | C4: 566.54545
A5: DPK | B5: May | C5: 595.71429
A6: AGO | B6: May | C6: 594.8
A7: AGO | B7: January | C7: 576.09091
A8: AGO | B8: June | C8: 574.38462
A9: DPK | B9: June | C9: 562.6
A10: PMS | B10: May | C10: 563.28571
A11: PMS | B11: March | C11: 540.30769
A12: PMS | B12: January | C12: 655.875
A13: PMS | B13: June | C13: 579.25
... A19: AGO | B19: February | C19: 601.5

Sheet Average Volume
A1: Product | B1: Depot | C1: Average Volumn
A2: DPK | B2: Apapa | C2: 24579.636
A3: DPK | B3: Ibadan | C3: 23880.333
A4: AGO | B4: Ibadan | C4: 21279.857
A5: AGO | B5: Calabar | C5: 25353.5
A6: DPK | B6: Kano | C6: 26123.818
A7: PMS | B7: Ibadan | C7: 22232.429
A8: PMS | B8: Kaduna | C8: 23785.857
A9: AGO | B9: Port Harcourt | C9: 21373.083
A10: PMS | B10: Kano | C10: 21284.833
A11: DPK | B11: Port Harcourt | C11: 24418.056
A12: PMS | B12: Port Harcourt | C12: 22370.941
A13: AGO | B13: Apapa | C13: 19983.154
... A19: AGO | B19: Kano | C19: 17892.222

Sheet Cleaned Data
A1: Fuel Sales Data For Jan-June 2025
A3: Transaction Date | B3: Month | C3: Product | D3: Region | E3: Depot | F3: Litres Sold | G3: Cost per Litre | H3: Selling Price per Litres | I3: Forex Rate | J3: Forex Band | K3: Logistics | L3: Revenue | M3: Profit | N3: Profit Status | O3: Profit Margin %
A4: 45728 | B4: March | C4: DPK | D4: South-West | E4: Apapa | F4: 24580 | G4: 601 | H4: 489 | I4: 1213 | J4: =IF(Sales_Data[[#This Row],[Forex Rate]]<900,"Below 900",IF(Sales_Data[[#This Row],[Forex Rate]]<1100,"900–1099",IF(Sales_Data[[#This Row],[Forex Rate]]<1300,"1100–1299","1300+"))) -> 1100–1299 | K4: 729903 | L4: 12019620 | M4: -3482863 | N4: =IF(Sales_Data[[#This Row],[Profit]]<0,"Loss","Profit") -> Loss | O4: -0.28976482
A5: 45714 | B5: February | C5: DPK | D5: South-West | E5: Ibadan | F5: 43618 | G5: 468 | H5: 520 | I5: 1352 | J5: =IF(Sales_Data[[#This Row],[Forex Rate]]<900,"Below 900",IF(Sales_Data[[#This Row],[Forex Rate]]<1100,"900–1099",IF(Sales_Data[[#This Row],[Forex Rate]]<1300,"1100–1299","1300+"))) -> 1300+ | K5: 680425 | L5: 22681360 | M5: 1587711 | N5: =IF(Sales_Data[[#This Row],[Profit]]<0,"Loss","Profit") -> Profit | O5: 0.070000697
A6: 45755 | B6: April | C6: DPK | D6: South-West | E6: Ibadan | F6: 23880 | G6: 567 | H6: 502 | I6: 1336 | J6: =IF(Sales_Data[[#This Row],[Forex Rate]]<900,"Below 900",IF(Sales_Data[[#This Row],[Forex Rate]]<1100,"900–1099",IF(Sales_Data[[#This Row],[Forex Rate]]<1300,"1100–1299","1300+"))) -> 1300+ | K6: 365840 | L6: 11987760 | M6: -1918040 | N6: =IF(Sales_Data[[#This Row],[Profit]]<0,"Loss","Profit") -> Loss | O6: -0.15999987
A7: 45793 | B7: May | C7: DPK | D7: South-West | E7: Ibadan | F7: 23880 | G7: 634 | H7: 742 | I7: 1560 | J7: =IF(Sales_Data[[#This Row],[Forex Rate]]<900,"Below 900",IF(Sales_Data[[#This Row],[Forex Rate]]<1100,"900–1099",IF(Sales_Data[[#This Row],[Forex Rate]]<1300,"1100–1299","1300+"))) -> 1300+ | K7: 267136 | L7: 17718960 | M7: 2311904 | N7: =IF(Sales_Data[[#This Row],[Profit]]<0,"Loss","Profit") -> Profit | O7: 0.13047628
A8: 45692 | B8: February | C8: DPK | D8: South-South | E8: Port Harcourt | F8: 24418 | G8: 550 | H8: 545 | I8: 1454 | J8: =IF(Sales_Data[[#This Row],[Forex Rate]]<900,"Below 900",IF(Sales_Data[[#This Row],[Forex Rate]]<1100,"900–1099",IF(Sales_Data[[#This Row],[Forex Rate]]<1300,"1100–1299","1300+"))) -> 1300+ | K8: 712262 | L8: 13307810 | M8: -834352 | N8: =IF(Sales_Data[[#This Row],[Profit]]<0,"Loss","Profit") -> Loss | O8: -0.062696417
A9: 45766 | B9: April | C9: DPK | D9: South-South | E9: Port Harcourt | F9: 23254 | G9: 567 | H9: 636 | I9: 1588 | J9: =IF(Sales_Data[[#This Row],[Forex Rate]]<900,"Below 900",IF(Sales_Data[[#This Row],[Forex Rate]]<1100,"900–1099",IF(Sales_Data[[#This Row],[Forex Rate]]<1300,"1100–1299","1300+"))) -> 1300+ | K9: 626156 | L9: 14789544 | M9: 978370 | N9: =IF(Sales_Data[[#This Row],[Profit]]<0,"Loss","Profit") -> Profit | O9: 0.066152817
A10: 45779 | B10: May | C10: DPK | D10: South-South | E10: Port Harcourt | F10: 17478 | G10: 526 | H10: 588 | I10: 1224 | J10: =IF(Sales_Data[[#This Row],[Forex Rate]]<900,"Below 900",IF(Sales_Data[[#This Row],[Forex Rate]]<1100,"900–1099",IF(Sales_Data[[#This Row],[Forex Rate]]<1300,"1100–1299","1300+"))) -> 1100–1299 | K10: 460735 | L10: 10277064 | M10: 622901 | N10: =IF(Sales_Data[[#This Row],[Profit]]<0,"Loss","Profit") -> Profit | O10: 0.060610793
A11: 45795 | B11: May | C11: AGO | D11: South-West | E11: Ibadan | F11: 21280 | G11: 609 | H11: 682 | I11: 1465 | J11: =IF(Sales_Data[[#This Row],[Forex Rate]]<900,"Below 900",IF(Sales_Data[[#This Row],[Forex Rate]]<1100,"900–1099",IF(Sales_Data[[#This Row],[Forex Rate]]<1300,"1100–1299","1300+"))) -> 1300+ | K11: 1096865 | L11: 14512960 | M11: 456575 | N11: =IF(Sales_Data[[#This Row],[Profit]]<0,"Loss","Profit") -> Profit | O11: 0.031459812
A12: 45673 | B12: January | C12: AGO | D12: South-West | E12: Ibadan | F12: 5141 | G12: 655 | H12: 763 | I12: 1262 | J12: =IF(Sales_Data[[#This Row],[Forex Rate]]<900,"Below 900",IF(Sales_Data[[#This Row],[Forex Rate]]<1100,"900–1099",IF(Sales_Data[[#This Row],[Forex Rate]]<1300,"1100–1299","1300+"))) -> 1100–1299 | K12: 680425 | L12: 3922583 | M12: -125197 | N12: =IF(Sales_Data[[#This Row],[Profit]]<0,"Loss","Profit") -> Loss | O12: -0.031916979
A13: 45686 | B13: January | C13: AGO | D13: South-South | E13: Port Harcourt | F13: 25153 | G13: 492 | H13: 512 | I13: 1591 | J13: =IF(Sales_Data[[#This Row],[Forex Rate]]<900,"Below 900",IF(Sales_Data[[#This Row],[Forex Rate]]<1100,"900–1099",IF(Sales_Data[[#This Row],[Forex Rate]]<1300,"1100–1299","1300+"))) -> 1300+ | K13: 891798 | L13: 12878336 | M13: -388738 | N13: =IF(Sales_Data[[#This Row],[Profit]]<0,"Loss","Profit") -> Loss | O13: -0.030185421
A14: 45820 | B14: June | C14: AGO | D14: South-South | E14: Calabar | F14: 29260 | G14: 574 | H14: 631 | I14: 1298 | J14: =IF(Sales_Data[[#This Row],[Forex Rate]]<900,"Below 900",IF(Sales_Data[[#This Row],[Forex Rate]]<1100,"900–1099",IF(Sales_Data[[#This Row],[Forex Rate]]<1300,"1100–1299","1300+"))) -> 1100–1299 | K14: 649484 | L14: 18463060 | M14: 1018336 | N14: =IF(Sales_Data[[#This Row],[Profit]]<0,"Loss","Profit") -> Profit | O14: 0.055155321
A15: 45833 | B15: June | C15: DPK | D15: North | E15: Kano | F15: 8665 | G15: 662 | H15: 874 | I15: 1389 | J15: =IF(Sales_Data[[#This Row],[Forex Rate]]<900,"Below 900",IF(Sales_Data[[#This Row],[Forex Rate]]<1100,"900–1099",IF(Sales_Data[[#This Row],[Forex Rate]]<1300,"1100–1299","1300+"))) -> 1300+ | K15: 349811 | L15: 7573210 | M15: 1487169 | N15: =IF(Sales_Data[[#This Row],[Profit]]<0,"Loss","Profit") -> Profit | O15: 0.19637234
... A303: 45800 | B303: May | C303: PMS | D303: South-South | E303: Port Harcourt | F303: 17067 | G303: 650 | H303: 587 | I303: 1261 | J303: =IF(Sales_Data[[#This Row],[Forex Rate]]<900,"Below 900",IF(Sales_Data[[#This Row],[Forex Rate]]<1100,"900–1099",IF(Sales_Data[[#This Row],[Forex Rate]]<1300,"1100–1299","1300+"))) -> 1100–1299 | K303: 642323 | L303: 10018329 | M303: -1717544 | N303: =IF(Sales_Data[[#This Row],[Profit]]<0,"Loss","Profit") -> Loss | O303: -0.17144017

Sheet Pivot Tables
A1: Revenue and Profit by Product | G1: Revenue and Profit by Region | L1: Deport Performance | R1: Monthly Sales Trend | W1: Impact of Forex Rate on Profit Performance | AC1: Profit And Loss Count
A3: Row Labels | B3: Sum of Profit | C3: Sum of Revenue | D3: Average of Profit Margin % | G3: Row Labels | H3: Sum of Revenue | I3: Sum of Profit | L3: Row Labels | M3: Sum of Profit | R3: Row Labels | S3: Sum of Profit | W3: Row Labels | X3: Sum of Profit | Y3: Average of Profit Margin % | AC3: Row Labels | AD3: Count of Profit Status | AG3: Total Revenue | AH3: Total Profit | AI3: Avg. Profit Margin | AJ3: Loss Rate% | AK3: High Forex Driven Profit
A4: AGO | B4: 119275926 | C4: 1582847896 | D4: 0.045654043 | G4: South-South | H4: 1748512762 | I4: 173275742 | L4: Apapa | M4: 43928693 | R4: Jan | S4: 20373686 | W4: 1100–1299 | X4: 41768043 | Y4: 0.025682796 | AC4: Loss | AD4: 81 | AG4: =VALUE(GETPIVOTDATA("Revenue",'Pivot Tables'!A3)) -> 4686197648 | AH4: =VALUE(GETPIVOTDATA("Profit",'Pivot Tables'!A3)) -> 388584892 | AI4: =GETPIVOTDATA("Profit Margin %", 'Pivot Tables'!A3) -> 0.058668151 | AJ4: =GETPIVOTDATA("Profit Status",$AC$3,"Profit Status","Loss")/GETPIVOTDATA("Profit Status",$AC$3) -> 0.27 | AK4: =GETPIVOTDATA("Sum of Profit",$W$3,"Forex Band","1300+")/GETPIVOTDATA("Sum of Profit",$W$3) -> 0.89251244
A5: DPK | B5: 128923844 | C5: 1573464747 | D5: 0.061739157 | G5: North | H5: 1563900170 | I5: 118306441 | L5: Calabar | M5: 108182825 | R5: Feb | S5: 86212681 | W5: 1300+ | X5: 346816849 | Y5: 0.064641876 | AC5: Profit | AD5: 219
A6: PMS | B6: 140385122 | C6: 1529885005 | D6: 0.069735355 | G6: South-West | H6: 1373784716 | I6: 97002709 | L6: Ibadan | M6: 53074016 | R6: Mar | S6: 72475123 | W6: Grand Total | X6: 388584892 | Y6: 0.058668151 | AC6: Grand Total | AD6: 300
A7: Grand Total | B7: 388584892 | C7: 4686197648 | D7: 0.058668151 | G7: Grand Total | H7: 4686197648 | I7: 388584892 | L7: Kaduna | M7: 66796895 | R7: Apr | S7: 99203907
L8: Kano | M8: 51509546 | R8: May | S8: 49408446
L9: Port Harcourt | M9: 65092917 | R9: Jun | S9: 60911049
L10: Grand Total | M10: 388584892 | R10: Grand Total | S10: 388584892

Sheet Helper Calculation
A1: Total Revenue | B1: =GETPIVOTDATA("Sum of Revenue",'Pivot Tables'!$A$3) -> 4686197648
A2: Total Profit | B2: =GETPIVOTDATA("Sum of Profit",'Pivot Tables'!$A$3) -> 388584892
A3: Average Profit Margin | B3: =B2 / B1 -> 0.082921149

Sheet Sales Performance Dashboard
